sdt/ProX.py
sdt/__init__.py
sdt.vip-1.1.2.dist-info/LICENSE
sdt.vip-1.1.2.dist-info/METADATA
sdt.vip-1.1.2.dist-info/WHEEL
sdt.vip-1.1.2.dist-info/top_level.txt
sdt.vip-1.1.2.dist-info/RECORD
