Metadata-Version: 2.1
Name: sdt.vip
Version: 1.1.2
Summary: cns工具包
Home-page: https://sdt.vip/example
Author: Rambo
Author-email: 6566666@qq.com
License: Copyright (C) 2023 CNS. All Rights Reserved. See LICENSE for license.
Platform: UNKNOWN
Classifier: Development Status :: 3 - Alpha
Classifier: Programming Language :: Python :: 3
Classifier: License :: OSI Approved :: MIT License
Classifier: Operating System :: Microsoft :: Windows
Requires-Python: >=3.6
License-File: LICENSE
Requires-Dist: python-dateutil
